ragcraft.py
ragcraft-0.1.5.dist-info/LICENSE
ragcraft-0.1.5.dist-info/METADATA
ragcraft-0.1.5.dist-info/WHEEL
ragcraft-0.1.5.dist-info/RECORD
